agent.py
config.py
session_manager.py
streaming_json.py
cli_agent/__init__.py
cli_agent/cli/__init__.py
cli_agent/core/__init__.py
cli_agent/core/api_client_manager.py
cli_agent/core/base_agent.py
cli_agent/core/base_llm_provider.py
cli_agent/core/base_provider.py
cli_agent/core/builtin_tool_executor.py
cli_agent/core/chat_interface.py
cli_agent/core/diff_display.py
cli_agent/core/display_manager.py
cli_agent/core/enhanced_streaming_json.py
cli_agent/core/event_system.py
cli_agent/core/formatting.py
cli_agent/core/formatting_utils.py
cli_agent/core/global_interrupt.py
cli_agent/core/input_handler.py
cli_agent/core/interrupt_aware_streaming.py
cli_agent/core/mcp_host.py
cli_agent/core/message_processor.py
cli_agent/core/model_config.py
cli_agent/core/permission_display.py
cli_agent/core/permission_socket.py
cli_agent/core/response_handler.py
cli_agent/core/slash_commands.py
cli_agent/core/subagent_coordinator.py
cli_agent/core/subprocess_display.py
cli_agent/core/system_prompt_builder.py
cli_agent/core/terminal_manager.py
cli_agent/core/terminal_state.py
cli_agent/core/token_manager.py
cli_agent/core/tool_call_processor.py
cli_agent/core/tool_execution_engine.py
cli_agent/core/tool_permissions.py
cli_agent/core/tool_schema.py
cli_agent/core/default_roles/analyst.yaml
cli_agent/core/default_roles/analyst_tools
cli_agent/core/default_roles/developer.yaml
cli_agent/core/default_roles/example-dynamic.yaml
cli_agent/core/default_roles/example-dynamic_tools
cli_agent/core/default_roles/research_director.yaml
cli_agent/core/default_roles/researcher.yaml
cli_agent/core/default_roles/researcher_tools
cli_agent/core/default_roles/security-expert.yaml
cli_agent/core/default_roles/security-expert_tools
cli_agent/core/default_roles/subagent.yaml
cli_agent/core/default_roles/subagent_tools
cli_agent/core/default_roles/summarizer.yaml
cli_agent/core/hooks/__init__.py
cli_agent/core/hooks/hook_config.py
cli_agent/core/hooks/hook_events.py
cli_agent/core/hooks/hook_executor.py
mcp_cli_agent-1.2.6.dist-info/licenses/LICENSE
mcp_cli_agent-1.2.6.dist-info/METADATA
mcp_cli_agent-1.2.6.dist-info/WHEEL
mcp_cli_agent-1.2.6.dist-info/entry_points.txt
mcp_cli_agent-1.2.6.dist-info/top_level.txt
mcp_cli_agent-1.2.6.dist-info/RECORD
