Metadata-Version: 2.4
Name: mcp-cli-agent
Version: 1.2.6
Summary: MCP-enabled AI assistant with tool integration
Home-page: https://github.com/amranu/cli-agent
Author: CLI Agent Team
Author-email: 
License: MIT
Project-URL: Homepage, https://github.com/amranu/cli-agent
Project-URL: Bug Reports, https://github.com/amranu/cli-agent/issues
Project-URL: Source Code, https://github.com/amranu/cli-agent
Keywords: ai,assistant,mcp,tools,cli,chatbot,deepseek,gemini
Classifier: Development Status :: 4 - Beta
Classifier: Intended Audience :: Developers
Classifier: License :: OSI Approved :: MIT License
Classifier: Operating System :: OS Independent
Classifier: Programming Language :: Python :: 3
Classifier: Programming Language :: Python :: 3.10
Classifier: Programming Language :: Python :: 3.11
Classifier: Programming Language :: Python :: 3.12
Classifier: Topic :: Software Development
Classifier: Topic :: Scientific/Engineering :: Artificial Intelligence
Requires-Python: >=3.8
License-File: LICENSE
Requires-Dist: mcp>=1.0.0
Requires-Dist: fastmcp>=2.0.0
Requires-Dist: openai>=1.0.0
Requires-Dist: google-genai>=1.0.0
Requires-Dist: httpx>=0.24.0
Requires-Dist: pydantic>=2.0.0
Requires-Dist: python-dotenv>=1.0.0
Requires-Dist: click>=8.0.0
Requires-Dist: prompt_toolkit>=3.0.0
Requires-Dist: rich>=13.0.0
Requires-Dist: requests>=2.28.0
Requires-Dist: tiktoken>=0.5.0
Requires-Dist: transformers>=4.30.0
Requires-Dist: anthropic>=0.25.0
Requires-Dist: PyYAML>=6.0.0
Requires-Dist: beautifulsoup4>=4.12.0
Requires-Dist: duckduckgo-search>=8.0.0
Requires-Dist: curl-cffi>=0.11.0
Requires-Dist: tls-client>=1.0.0
Provides-Extra: test
Requires-Dist: pytest>=7.0.0; extra == "test"
Requires-Dist: pytest-asyncio>=0.21.0; extra == "test"
Requires-Dist: pytest-cov>=4.0.0; extra == "test"
Requires-Dist: pytest-mock>=3.10.0; extra == "test"
Requires-Dist: pytest-timeout>=2.1.0; extra == "test"
Requires-Dist: pytest-xdist>=3.0.0; extra == "test"
Requires-Dist: coverage>=7.0.0; extra == "test"
Provides-Extra: dev
Requires-Dist: black>=23.0.0; extra == "dev"
Requires-Dist: isort>=5.12.0; extra == "dev"
Requires-Dist: flake8>=6.0.0; extra == "dev"
Requires-Dist: mypy>=1.0.0; extra == "dev"
Requires-Dist: bandit>=1.7.0; extra == "dev"
Requires-Dist: safety>=2.0.0; extra == "dev"
Dynamic: home-page
Dynamic: license-file
Dynamic: requires-python
